cmem_plugin_jq/__init__.py
cmem_plugin_jq/common.py
cmem_plugin_jq/jq.svg
cmem_plugin_jq/operator.py
cmem_plugin_jq/task.py
cmem_plugin_jq-0.7.0.dist-info/METADATA
cmem_plugin_jq-0.7.0.dist-info/WHEEL
cmem_plugin_jq-0.7.0.dist-info/licenses/LICENSE
cmem_plugin_jq-0.7.0.dist-info/RECORD
